<?xml version="1.0" ?>
<Maps folder="/home/wenfeng/Desktop/LPFCQDJB31/Map">
    <Map mapID="0101" path="0101.map" />
    <Map mapID="0102" path="0102.map" />
    <Map mapID="0103" path="0103.map" />
    <Map mapID="0104" path="0104.map" />
    <Map mapID="0105" path="0105.map" />
    <Map mapID="0106" path="0106.map" />
    <Map mapID="0201" path="0201.map" />
    <Map mapID="0202" path="0202.map" />
    <Map mapID="0203" path="0203.map" />
    <Map mapID="0204" path="0204.map" />
    <Map mapID="0205" path="0205.map" />
    <Map mapID="0206" path="0206.map" />
    <Map mapID="0207" path="0207.map" />
    <Map mapID="0208" path="0208.map" />
    <Map mapID="0209" path="0209.map" />
    <Map mapID="0210" path="0210.map" />
    <Map mapID="0301" path="0301.map" />
    <Map mapID="0302" path="0302.map" />
    <Map mapID="0303" path="0303.map" />
    <Map mapID="0304" path="0304.map" />
    <Map mapID="0305" path="0305.map" />
    <Map mapID="0306" path="0306.map" />
    <Map mapID="0307" path="0307.map" />
    <Map mapID="0401" path="0401.map" />
    <Map mapID="0501" path="0501.map" />
    <Map mapID="0601" path="0601.map" />
    <Map mapID="0701" path="0701.map" />
    <Map mapID="0702" path="0702.map" />
    <Map mapID="0801" path="0801.map" />
    <Map mapID="0901" path="0901.map" />
    <Map mapID="1001" path="1001.map" />
    <Map mapID="1101" path="1101.map" />
    <Map mapID="1201" path="1201.map" />
    <Map mapID="1202" path="1202.map" />
    <Map mapID="1203" path="1203.map" />
    <Map mapID="1204" path="1204.map" />
    <Map mapID="1301" path="1301.map" />
    <Map mapID="1302" path="1302.map" />
    <Map mapID="1401" path="1401.map" />
    <Map mapID="1501" path="1501.map" />
    <Map mapID="1601" path="1601.map" />
    <Map mapID="1701" path="1701.map" />
    <Map mapID="1801" path="1801.map" />
    <Map mapID="1901" path="1901.map" />
    <Map mapID="2001" path="2001.map" />
    <Map mapID="2101" path="2101.map" />
    <Map mapID="2102" path="2102.map" />
    <Map mapID="2103" path="2103.map" />
    <Map mapID="2201" path="2201.map" />
    <Map mapID="2301" path="2301.map" />
    <Map mapID="2401" path="2401.map" />
    <Map mapID="2501" path="2501.map" />
    <Map mapID="2601" path="2601.map" />
    <Map mapID="2701" path="2701.map" />
    <Map mapID="2801" path="2801.map" />
    <Map mapID="2901" path="2901.map" />
    <Map mapID="3001" path="3001.map" />
    <Map mapID="3101" path="3101.map" />
    <Map mapID="3201" path="3201.map" />
    <Map mapID="3301" path="3301.map" />
    <Map mapID="3302" path="3302.map" />
    <Map mapID="3303" path="3303.map" />
    <Map mapID="3304" path="3304.map" />
    <Map mapID="3401" path="3401.map" />
    <Map mapID="3402" path="3402.map" />
    <Map mapID="3501" path="3501.map" />
    <Map mapID="3502" path="3502.map" />
    <Map mapID="3503" path="3503.map" />
    <Map mapID="3504" path="3504.map" />
    <Map mapID="3505" path="3505.map" />
    <Map mapID="3601" path="3601.map" />
    <Map mapID="3602" path="3602.map" />
    <Map mapID="3603" path="3603.map" />
    <Map mapID="3701" path="3701.map" />
    <Map mapID="3801" path="3801.map" />
    <Map mapID="3901" path="3901.map" />
    <Map mapID="3902" path="3902.map" />
    <Map mapID="4001" path="4001.map" />
    <Map mapID="4101" path="4101.map" />
    <Map mapID="4201" path="4201.map" />
    <Map mapID="4301" path="4301.map" />
    <Map mapID="4302" path="4302.map" />
    <Map mapID="4303" path="4303.map" />
    <Map mapID="4401" path="4401.map" />
    <Map mapID="4402" path="4402.map" />
    <Map mapID="4501" path="4501.map" />
    <Map mapID="4502" path="4502.map" />
    <Map mapID="4601" path="4601.map" />
    <Map mapID="4602" path="4602.map" />
    <Map mapID="4701" path="4701.map" />
    <Map mapID="4801" path="4801.map" />
    <Map mapID="4901" path="4901.map" />
    <Map mapID="5001" path="5001.map" />
    <Map mapID="5002" path="5002.map" />
    <Map mapID="5101" path="5101.map" />
</Maps>